CONTRIBUTORS
LICENSE
MANIFEST.in
README
README.md
VERSION
docker-hica
setup.py
base/__init__.py
base/hica_base.py
docker_hica.egg-info/PKG-INFO
docker_hica.egg-info/SOURCES.txt
docker_hica.egg-info/dependency_links.txt
docker_hica.egg-info/requires.txt
docker_hica.egg-info/top_level.txt
docs/cmdaliases.md
docs/dockerfile-guidelines.md
docs/labels.md
docs/selinux.md
injectors/.bind_pwd.py.swp
injectors/bind_home.py
injectors/bind_home.pyc
injectors/bind_localtime.py
injectors/bind_localtime.pyc
injectors/bind_pwd.py
injectors/bind_pwd.pyc
injectors/bind_user_groups.py
injectors/bind_user_groups.pyc
injectors/cuda.py
injectors/cuda.pyc
injectors/dri_passthrough.py
injectors/dri_passthrough.pyc
injectors/env_passthrough.py
injectors/env_passthrough.pyc
injectors/introspect_runtime.py
injectors/introspect_runtime.pyc
injectors/kvm_passthrough.py
injectors/kvm_passthrough.pyc
injectors/machine_id.py
injectors/machine_id.pyc
injectors/pulse.py
injectors/pulse.pyc
injectors/sound_device.py
injectors/sound_device.pyc
injectors/tty.py
injectors/xsocket.py
injectors/xsocket.pyc