Metadata-Version: 1.0
Name: docker-hica
Version: 0.5.1
Summary: The goal of this project is to define a set of image label metadata and launcher tooling that understands said metadata to provide for smooth experience running containerized applications with tight integration with the host operating system.
Home-page: https://github.com/shaded-enmity/docker-hica
Author: Pavel Odvody
Author-email: podvody@redhat.com
License: MIT
Keywords: docker host integrated container application
Platform: UNKNOWN
